pokesummary/__init__.py
pokesummary/__main__.py
pokesummary/data/__init__.py
pokesummary/data/pokemon_modified.csv
pokesummary/data/type_defenses_modified.csv
pokesummary/model.py
pokesummary/view.py
pokesummary-2.1.0.dist-info/entry_points.txt
pokesummary-2.1.0.dist-info/LICENSE.txt
pokesummary-2.1.0.dist-info/WHEEL
pokesummary-2.1.0.dist-info/METADATA
pokesummary-2.1.0.dist-info/RECORD
