Metadata-Version: 2.1
Name: pokesummary
Version: 2.1.0
Summary: An easy-to-use, informative command line interface (CLI) for accessing Pokémon summaries.
Home-page: https://github.com/tactlessfish/pokesummary
License: MIT
Author: Fisher Sun
Author-email: fisher521.fs@gmail.com
Requires-Python: >=3.7,<4.0
Classifier: License :: OSI Approved :: MIT License
Classifier: Programming Language :: Python :: 3
Classifier: Programming Language :: Python :: 3.10
Classifier: Programming Language :: Python :: 3.7
Classifier: Programming Language :: Python :: 3.8
Classifier: Programming Language :: Python :: 3.9
Project-URL: Repository, https://github.com/tactlessfish/pokesummary
